{
  "tech_l1": "科技",
  "themes": [
    {
      "l2": "AI算力与数据中心",
      "l3": "算力基础设施",
      "priority": 20,
      "source_boards": ["东数西算(算力)", "算力租赁", "数据中心(AIDC)", "英伟达概念", "华为昇腾"]
    },
    {
      "l2": "AI算力与数据中心",
      "l3": "液冷温控",
      "priority": 8,
      "source_boards": ["液冷服务器"]
    },
    {
      "l2": "光通信与高速互联",
      "l3": "光模块/CPO",
      "priority": 5,
      "source_boards": ["共封装光学(CPO)", "光纤概念"]
    },
    {
      "l2": "光通信与高速互联",
      "l3": "铜缆高速连接",
      "priority": 20,
      "source_boards": ["铜缆高速连接"]
    },
    {
      "l2": "PCB与电子制造",
      "l3": "PCB",
      "priority": 5,
      "source_boards": ["PCB概念"]
    },
    {
      "l2": "半导体与先进封装",
      "l3": "芯片/半导体",
      "priority": 30,
      "source_boards": ["芯片概念", "第三代半导体", "MCU芯片", "存储芯片", "华为海思概念股"]
    },
    {
      "l2": "半导体与先进封装",
      "l3": "先进封装",
      "priority": 15,
      "source_boards": ["先进封装"]
    },
    {
      "l2": "半导体与先进封装",
      "l3": "半导体设备材料",
      "priority": 25,
      "source_boards": ["光刻机", "光刻胶"]
    },
    {
      "l2": "软件AI与信创",
      "l3": "AI应用",
      "priority": 40,
      "source_boards": ["人工智能", "AI应用", "多模态AI", "AI智能体", "AI语料", "AI视频", "智谱AI"]
    },
    {
      "l2": "软件AI与信创",
      "l3": "信创与数据要素",
      "priority": 45,
      "source_boards": ["信创", "数据要素", "网络安全", "华为鲲鹏", "华为欧拉", "华为盘古"]
    },
    {
      "l2": "AI终端与消费电子",
      "l3": "AI终端",
      "priority": 35,
      "source_boards": ["AI PC", "AI手机", "AI眼镜", "华为手机"]
    },
    {
      "l2": "AI终端与消费电子",
      "l3": "消费电子",
      "priority": 55,
      "source_boards": ["消费电子概念", "苹果概念", "华为概念"]
    },
    {
      "l2": "机器人与智能汽车",
      "l3": "机器人",
      "priority": 45,
      "source_boards": ["机器人概念", "人形机器人"]
    },
    {
      "l2": "机器人与智能汽车",
      "l3": "智能汽车",
      "priority": 60,
      "source_boards": ["无人驾驶", "汽车电子", "汽车芯片", "华为汽车", "小米汽车"]
    }
  ],
  "board_code_overrides": {
    "光纤概念": "309151",
    "智谱AI": "309164",
    "华为盘古": "309170",
    "AI眼镜": "309152",
    "华为手机": "309167"
  },
  "manual_stock_tags": {
    "300476": [{"l2": "PCB与电子制造", "l3": "PCB", "priority": 1, "source_board": "人工锚点:胜宏科技"}],
    "601138": [{"l2": "AI算力与数据中心", "l3": "算力服务器", "priority": 1, "source_board": "人工锚点:工业富联"}],
    "300394": [{"l2": "光通信与高速互联", "l3": "光模块/CPO", "priority": 1, "source_board": "人工锚点:天孚通信"}],
    "002837": [{"l2": "AI算力与数据中心", "l3": "液冷温控", "priority": 1, "source_board": "人工锚点:英维克"}]
  },
  "tech_industry_fallbacks": [
    {
      "keywords": ["软件和信息技术服务业", "互联网", "信息传输"],
      "l2": "软件AI与信创",
      "l3": "软件信息服务",
      "priority": 90
    },
    {
      "keywords": ["计算机、通信和其他电子设备制造业"],
      "l2": "电子制造与通信设备",
      "l3": "其他电子通信",
      "priority": 95
    }
  ]
}
